pybox/pybox.py
pybox/__init__.py
pypybox-0.1.dist-info/top_level.txt
pypybox-0.1.dist-info/METADATA
pypybox-0.1.dist-info/RECORD
pypybox-0.1.dist-info/DESCRIPTION.rst
pypybox-0.1.dist-info/entry_points.txt
pypybox-0.1.dist-info/metadata.json
pypybox-0.1.dist-info/WHEEL
