Metadata-Version: 2.0
Name: pypybox
Version: 0.1
Summary: Boxes in your CLI
Home-page: http://github.com/JustB/pybox
Author: Giustino Borzacchiello
Author-email: giustinob@gmail.com
License: MIT
Platform: UNKNOWN
Classifier: Development Status :: 3 - Alpha
Classifier: Intended Audience :: Developers
Classifier: Topic :: Utilities
Classifier: License :: OSI Approved :: MIT License
Classifier: Programming Language :: Python :: 2
Classifier: Programming Language :: Python :: 2.6
Classifier: Programming Language :: Python :: 2.7
Requires-Dist: docopt
